odoo10_addon_product_analytic_purchase-10.0.1.0.0-py2.7-nspkg.pth
odoo/addons/product_analytic_purchase/README.rst
odoo/addons/product_analytic_purchase/__init__.py
odoo/addons/product_analytic_purchase/__manifest__.py
odoo/addons/product_analytic_purchase/models/__init__.py
odoo/addons/product_analytic_purchase/models/purchase_order_line.py
odoo/addons/product_analytic_purchase/tests/__init__.py
odoo/addons/product_analytic_purchase/tests/test_purchase.py
odoo10_addon_product_analytic_purchase-10.0.1.0.0.dist-info/DESCRIPTION.rst
odoo10_addon_product_analytic_purchase-10.0.1.0.0.dist-info/METADATA
odoo10_addon_product_analytic_purchase-10.0.1.0.0.dist-info/RECORD
odoo10_addon_product_analytic_purchase-10.0.1.0.0.dist-info/WHEEL
odoo10_addon_product_analytic_purchase-10.0.1.0.0.dist-info/metadata.json
odoo10_addon_product_analytic_purchase-10.0.1.0.0.dist-info/namespace_packages.txt
odoo10_addon_product_analytic_purchase-10.0.1.0.0.dist-info/top_level.txt
